moremodels/__init__.py
moremodels/core.py
moremodels-1.0.51.dist-info/LICENSE
moremodels-1.0.51.dist-info/METADATA
moremodels-1.0.51.dist-info/WHEEL
moremodels-1.0.51.dist-info/top_level.txt
moremodels-1.0.51.dist-info/RECORD
