Metadata-Version: 2.1
Name: moremodels
Version: 1.0.51
Summary: More options to ensemble your models
Home-page: https://github.com/AbdelRahmanYaghi/moremodels
Author: AbdelRahman Yaghi
Author-email: abd20200355@std.psut.edu.jo
Project-URL: Bug Tracker, https://github.com/AbdelRahmanYaghi/moremodels/issues
Classifier: Programming Language :: Python :: 3
Classifier: License :: OSI Approved :: MIT License
Classifier: Operating System :: OS Independent
Requires-Python: >=3.6
License-File: LICENSE
